odoo/addons/sentry/README.rst
odoo/addons/sentry/__init__.py
odoo/addons/sentry/__manifest__.py
odoo/addons/sentry/const.py
odoo/addons/sentry/generalutils.py
odoo/addons/sentry/hooks.py
odoo/addons/sentry/logutils.py
odoo/addons/sentry/processor.py
odoo/addons/sentry/i18n/ca.po
odoo/addons/sentry/i18n/sentry.pot
odoo/addons/sentry/i18n/zh_CN.po
odoo/addons/sentry/readme/CONFIGURE.rst
odoo/addons/sentry/readme/CONTRIBUTORS.rst
odoo/addons/sentry/readme/CREDITS.rst
odoo/addons/sentry/readme/DESCRIPTION.rst
odoo/addons/sentry/readme/INSTALL.rst
odoo/addons/sentry/readme/ROADMAP.rst
odoo/addons/sentry/readme/USAGE.rst
odoo/addons/sentry/static/description/icon.png
odoo/addons/sentry/static/description/index.html
odoo/addons/sentry/tests/__init__.py
odoo/addons/sentry/tests/test_client.py
odoo/addons/sentry/tests/test_logutils.py
odoo14_addon_sentry-14.0.3.0.2.dist-info/METADATA
odoo14_addon_sentry-14.0.3.0.2.dist-info/WHEEL
odoo14_addon_sentry-14.0.3.0.2.dist-info/top_level.txt
odoo14_addon_sentry-14.0.3.0.2.dist-info/RECORD
