Metadata-Version: 2.1
Name: odoo14-addon-sentry
Version: 14.0.3.0.2
Summary: Report Odoo errors to Sentry
Home-page: https://github.com/OCA/server-tools
Author: Mohammed Barsi,Versada,Nicolas JEUDY,Odoo Community Association (OCA),Vauxoo
Author-email: support@odoo-community.org
License: AGPL-3
Classifier: Programming Language :: Python
Classifier: Framework :: Odoo
Classifier: Framework :: Odoo :: 14.0
Classifier: License :: OSI Approved :: GNU Affero General Public License v3
Requires-Python: >=3.6
Requires-Dist: odoo <14.1dev,>=14.0a
Requires-Dist: sentry-sdk <=1.9.0
